LICENSE
MANIFEST.in
README.md
install.py
setup.py
grappetech_neocli.egg-info/PKG-INFO
grappetech_neocli.egg-info/SOURCES.txt
grappetech_neocli.egg-info/dependency_links.txt
grappetech_neocli.egg-info/entry_points.txt
grappetech_neocli.egg-info/not-zip-safe
grappetech_neocli.egg-info/requires.txt
grappetech_neocli.egg-info/top_level.txt
neocli/__init__.py
neocli/app.py
neocli/bench.py
neocli/cli.py
neocli/exceptions.py
neocli/prepare_beta_release.py
neocli/release.py
neocli/commands/__init__.py
neocli/commands/config.py
neocli/commands/git.py
neocli/commands/install.py
neocli/commands/make.py
neocli/commands/setup.py
neocli/commands/update.py
neocli/commands/utils.py
neocli/config/__init__.py
neocli/config/common_site_config.py
neocli/config/lets_encrypt.py
neocli/config/nginx.py
neocli/config/procfile.py
neocli/config/production_setup.py
neocli/config/redis.py
neocli/config/site_config.py
neocli/config/supervisor.py
neocli/config/systemd.py
neocli/config/templates/502.html
neocli/config/templates/Procfile
neocli/config/templates/bench_manager_nginx.conf
neocli/config/templates/frappe_sudoers
neocli/config/templates/letsencrypt.cfg
neocli/config/templates/nginx.conf
neocli/config/templates/nginx_default.conf
neocli/config/templates/redis_cache.conf
neocli/config/templates/redis_queue.conf
neocli/config/templates/redis_socketio.conf
neocli/config/templates/supervisor.conf
neocli/config/templates/systemd/frappe-bench-frappe-default-worker.service
neocli/config/templates/systemd/frappe-bench-frappe-long-worker.service
neocli/config/templates/systemd/frappe-bench-frappe-schedule.service
neocli/config/templates/systemd/frappe-bench-frappe-short-worker.service
neocli/config/templates/systemd/frappe-bench-frappe-web.service
neocli/config/templates/systemd/frappe-bench-node-socketio.service
neocli/config/templates/systemd/frappe-bench-redis-cache.service
neocli/config/templates/systemd/frappe-bench-redis-queue.service
neocli/config/templates/systemd/frappe-bench-redis-socketio.service
neocli/config/templates/systemd/frappe-bench-redis.target
neocli/config/templates/systemd/frappe-bench-web.target
neocli/config/templates/systemd/frappe-bench-workers.target
neocli/config/templates/systemd/frappe-bench.target
neocli/patches/__init__.py
