Metadata-Version: 2.1
Name: grappetech-neocli
Version: 5.0.0.dev0
Summary: CLI to manage Multi-tenant deployments for Neo modules
Home-page: https://erpneo.app/neocli
Author: Grappe Technology Ltd
Author-email: ola@erpneo.app
License: GPLv3
Project-URL: Documentation, https://grappetech.com/docs/user/en/neocli
Project-URL: Source, https://github.com/grappetech/neocli
Project-URL: Changelog, https://github.com/grappetech/neocli/releases
Platform: UNKNOWN
Classifier: Development Status :: 5 - Production/Stable
Classifier: Environment :: Console
Classifier: License :: OSI Approved :: GNU Affero General Public License v3
Classifier: Natural Language :: English
Classifier: Operating System :: MacOS
Classifier: Operating System :: OS Independent
Classifier: Topic :: Software Development :: Build Tools
Classifier: Topic :: Software Development :: User Interfaces
Classifier: Topic :: System :: Installation/Setup
Requires-Python: ~=3.6
License-File: LICENSE
